megadata/__init__.py
megadata/__main__.py
megadata/bizkv.py
megadata/clt_ipc.py
megadata/clt_web.py
megadata/myeval.py
megadata/mypy.py
megadata/mypyx.py
megadata/mywin.py
megadata/svr_echo.py
megadata/svr_ipc.py
megadata/svr_ipc_async.py
megadata/svr_ipc_bin.py
megadata/svr_ipcm.py
megadata/svr_nng.py
megadata-0.0.78.dist-info/LICENSE
megadata-0.0.78.dist-info/METADATA
megadata-0.0.78.dist-info/WHEEL
megadata-0.0.78.dist-info/top_level.txt
megadata-0.0.78.dist-info/RECORD
