Metadata-Version: 2.1
Name: megadata
Version: 0.0.78
Summary: tools from/for megadata
Author-email: Wanjo Chan <wanjochan@gmail.com>
Project-URL: Homepage, https://github.com/wanjo-tech/megadata
Classifier: Programming Language :: Python :: 3
Classifier: License :: OSI Approved :: MIT License
Classifier: Operating System :: OS Independent
Requires-Python: >=3.6
License-File: LICENSE
